biweeklybudget/__init__.py
biweeklybudget/backfill_ofx.py
biweeklybudget/biweeklypayperiod.py
biweeklybudget/cliutils.py
biweeklybudget/db.py
biweeklybudget/db_event_handlers.py
biweeklybudget/initdb.py
biweeklybudget/interest.py
biweeklybudget/load_data.py
biweeklybudget/ofxgetter.py
biweeklybudget/plaid_updater.py
biweeklybudget/prime_rate.py
biweeklybudget/screenscraper.py
biweeklybudget/settings.py
biweeklybudget/settings_example.py
biweeklybudget/utils.py
biweeklybudget/vault.py
biweeklybudget/version.py
biweeklybudget/wishlist2project.py
biweeklybudget/alembic/alembic.ini
biweeklybudget/alembic/env.py
biweeklybudget/alembic/versions/04e61490804b_add_budgettransaction_model.py
biweeklybudget/alembic/versions/073142f641b3_account_remove_re_field_defaults.py
biweeklybudget/alembic/versions/08b6358a04bf_txnreconcile_allow_txn_id_to_be_null.py
biweeklybudget/alembic/versions/1bb9e6a1c07c_add_scheduledtransaction_sales_tax_field.py
biweeklybudget/alembic/versions/32b34a664b5a_add_db_settings_table.py
biweeklybudget/alembic/versions/5446559aecf7_txnreconcile_txn_id_not_null.py
biweeklybudget/alembic/versions/61e62ef50513_add_transfer_relationships_to_.py
biweeklybudget/alembic/versions/6d37400ea9cd_add_omit_from_graphs_boolean_to_budget_.py
biweeklybudget/alembic/versions/7477ff15e8c4_base.py
biweeklybudget/alembic/versions/8627a80874a6_add_vehicle_and_fuellog_models.py
biweeklybudget/alembic/versions/9dc8545963be_account_interest_and_payoff_attributes.py
biweeklybudget/alembic/versions/a8f1228af250_add_account_negate_ofx_amounts_field.py
biweeklybudget/alembic/versions/ac93b5c826a5_add_plaid_item_id_and_plaid_token_.py
biweeklybudget/alembic/versions/bbb39e1d7c5d_add_weekly_and_annual_scheduled_.py
biweeklybudget/alembic/versions/ceb73ddf66eb_add_project_and_bomitem_models.py
biweeklybudget/alembic/versions/d01774fa3ae3_add_transaction_field_to_store_sales_.py
biweeklybudget/alembic/versions/ed827c515edb_account_add_do_not_reconcile_boolean.py
biweeklybudget-1.5.0.dist-info/licenses/LICENSE
biweeklybudget-1.5.0.dist-info/METADATA
biweeklybudget-1.5.0.dist-info/WHEEL
biweeklybudget-1.5.0.dist-info/entry_points.txt
biweeklybudget-1.5.0.dist-info/top_level.txt
biweeklybudget-1.5.0.dist-info/RECORD
