Metadata-Version: 2.4
Name: biweeklybudget
Version: 1.5.0
Summary: Responsive Flask/SQLAlchemy personal finance app, specifically for biweekly budgeting.
Home-page: https://github.com/jantman/biweeklybudget
Author: Jason Antman
Author-email: jason@jasonantman.com
Keywords: budget finance biweekly ofx flask responsive sqlalchemy bank
Classifier: Development Status :: 4 - Beta
Classifier: Environment :: Web Environment
Classifier: Framework :: Flask
Classifier: Intended Audience :: End Users/Desktop
Classifier: License :: OSI Approved :: GNU Affero General Public License v3 or later (AGPLv3+)
Classifier: Natural Language :: English
Classifier: Operating System :: POSIX
Classifier: Programming Language :: Python
Classifier: Programming Language :: Python :: 3 :: Only
Classifier: Programming Language :: Python :: 3
Classifier: Programming Language :: Python :: 3.14
Classifier: Topic :: Office/Business :: Financial
License-File: LICENSE
Requires-Dist: Flask==3.1.2
Requires-Dist: Jinja2==3.1.6
Requires-Dist: Mako==1.3.10
Requires-Dist: MarkupSafe==3.0.3
Requires-Dist: PyMySQL==1.1.2
Requires-Dist: SQLAlchemy-Utc==0.14.0
Requires-Dist: SQLAlchemy==2.0.45
Requires-Dist: SecretStorage==3.5.0
Requires-Dist: alembic==1.18.1
Requires-Dist: appdirs==1.4.4
Requires-Dist: asn1crypto==1.5.1
Requires-Dist: babel==2.17.0
Requires-Dist: beautifulsoup4==4.14.3
Requires-Dist: cffi==2.0.0
Requires-Dist: click==8.3.1
Requires-Dist: cryptography
Requires-Dist: datatables==0.4.9
Requires-Dist: httplib2==0.31.1
Requires-Dist: humanize==4.15.0
Requires-Dist: hvac==2.4.0
Requires-Dist: idna==3.11
Requires-Dist: itsdangerous==2.2.0
Requires-Dist: keyring==25.7.0
Requires-Dist: lxml==6.0.2
Requires-Dist: newrelic==11.2.0
Requires-Dist: nulltype==2.3.1
Requires-Dist: ofxhome==0.3.3
Requires-Dist: ofxparse==0.21
Requires-Dist: packaging
Requires-Dist: plaid-python==38.0.0
Requires-Dist: pycparser==2.23
Requires-Dist: pyparsing==3.3.1
Requires-Dist: python-dateutil==2.9.0.post0
Requires-Dist: python-editor==1.0.4
Requires-Dist: pytz
Requires-Dist: requests
Requires-Dist: selenium==4.39.0
Requires-Dist: six==1.17.0
Requires-Dist: versionfinder>=1.0.0
Requires-Dist: wishlist==0.5.3
Requires-Dist: Werkzeug==3.1.5
Dynamic: author
Dynamic: author-email
Dynamic: classifier
Dynamic: description
Dynamic: home-page
Dynamic: keywords
Dynamic: license-file
Dynamic: requires-dist
Dynamic: summary
